textdungeon/__init__.py
textdungeon/color.py
textdungeon/dungeon.py
textdungeon/entities.py
textdungeon/extra.py
textdungeon/items.py
textdungeon/main.py
textdungeon-6.9.dist-info/METADATA
textdungeon-6.9.dist-info/WHEEL
textdungeon-6.9.dist-info/entry_points.txt
textdungeon-6.9.dist-info/RECORD
