Metadata-Version: 2.1
Name: textdungeon
Version: 6.9
Summary: suffer alone in your terminal!
Home-page: https://github.com/Masbender/text-dungeon
License: MIT
Keywords: text,dungeon,game
Author: Matthew Bender
Author-email: matthewbender65@gmail.com
Maintainer: Noah Dinan
Maintainer-email: noah@shinysocks.net
Requires-Python: >=3.7,<4.0
Classifier: License :: OSI Approved :: MIT License
Classifier: Programming Language :: Python :: 3
Classifier: Programming Language :: Python :: 3.7
Classifier: Programming Language :: Python :: 3.8
Classifier: Programming Language :: Python :: 3.9
Classifier: Programming Language :: Python :: 3.10
Classifier: Programming Language :: Python :: 3.11
Project-URL: Repository, https://github.com/Masbender/text-dungeon
